[{
  "_id": {
    "$oid": "62c04c4e97ef58b32f2c2e57"
  },
  "league": "Англия",
  "date": "2022-06-24 12:00:00",
  "place": "Мельбурн Крикет Граунд",
  "commands": [
    {
      "name": "Бавария"
    },
    {
      "name": "Ливерпуль"
    }
  ],
  "winner": "Бавария"
},{
  "_id": {
    "$oid": "62c04c4e97ef58b32f2c2e58"
  },
  "league": "Испания",
  "date": "2022-07-24 12:00:00",
  "place": "Соккер Сити",
  "commands": [
    {
      "name": "Реал Мадрид"
    },
    {
      "name": "Манчестер Сити"
    }
  ],
  "winner": "Манчестер Сити"
}]